[{"href":"https://www.mi.com/seckill","name":"小米圈铁四单元耳机 黑色","desc":"给热爱音乐的你","imgurl":"//cdn.cnbj0.fds.api.mi-img.com/b2c-shopapi-pms/pms_1571384720.99968563.jpg?thumb=1&w=200&h=200","price":"798元\n                            999元"},{"href":"https://www.mi.com/seckill","name":"玺佳机械表·T系列 太空TR90 红色","desc":"颠覆创新—腕间悬浮时光","imgurl":"//cdn.cnbj0.fds.api.mi-img.com/b2c-shopapi-pms/pms_1573198119.54049236.jpg?thumb=1&w=200&h=200","price":"499元\n                            599元"},{"href":"https://www.mi.com/seckill","name":"工程挖掘机 白色","desc":"全新炫酷外观，工程系列豪华升级","imgurl":"//cdn.cnbj0.fds.api.mi-img.com/b2c-shopapi-pms/pms_1572939589.21071305.jpg?thumb=1&w=200&h=200","price":"168元\n                            199元"},{"href":"https://www.mi.com/seckill","name":"小米净水器S1 800G 白色","desc":"RO反渗透精滤，直饮健康纯水","imgurl":"//cdn.cnbj0.fds.api.mi-img.com/b2c-shopapi-pms/pms_1573027813.58597871.jpg?thumb=1&w=200&h=200","price":"2499元\n                            2999元"},{"href":"https://www.mi.com/seckill","name":"米兔儿童滑板车 粉","desc":"安全好玩的酷玩具","imgurl":"//cdn.cnbj0.fds.api.mi-img.com/b2c-shopapi-pms/pms_1553483956.58434790.jpg?thumb=1&w=200&h=200","price":"219元\n                            249元"},{"href":"https://www.mi.com/seckill","name":"米家扫拖机器人 黑色","desc":"扫得干净，拖得彻底","imgurl":"//cdn.cnbj0.fds.api.mi-img.com/b2c-shopapi-pms/pms_1573714515.51751293.jpg?thumb=1&w=200&h=200","price":"1799元\n                            1999元"},{"href":"https://www.mi.com/seckill","name":"米家蓝牙温湿度计2 三个装","desc":"冷暖干湿,一望而知","imgurl":"//cdn.cnbj0.fds.api.mi-img.com/b2c-shopapi-pms/pms_1575878173.84429959.jpg?thumb=1&w=200&h=200","price":"69元\n                            87元"},{"href":"https://www.mi.com/seckill","name":"最生活毛巾·Air（10条装） 白色+素蓝","desc":"给生活一条好毛巾","imgurl":"//cdn.cnbj1.fds.api.mi-img.com/mi-mall/2212bbd7c00dbb8ed1db3d6b9ee2341c.jpg?thumb=1&w=200&h=200&f=webp&q=90","price":"99元\n                            169元"},{"href":"https://www.mi.com/seckill","name":"智能积木 越野四驱车 白色","desc":"搭建快乐，操控激情","imgurl":"//cdn.cnbj0.fds.api.mi-img.com/b2c-shopapi-pms/pms_1560161198.36395117.jpg?thumb=1&w=200&h=200","price":"689元\n                            699元"},{"href":"https://www.mi.com/seckill","name":"米家扫地机器人1S 白色","desc":"看得明白扫得彻底","imgurl":"//cdn.cnbj0.fds.api.mi-img.com/b2c-shopapi-pms/pms_1553760277.63282202.jpg?thumb=1&w=200&h=200","price":"1695元\n                            1999元"},{"href":"https://www.mi.com/seckill","name":"小米米家智能摄像机云台版 白","desc":"高清画质，守护家的每一面","imgurl":"//cdn.cnbj0.fds.api.mi-img.com/b2c-shopapi-pms/pms_1567393585.49577260.jpg?thumb=1&w=200&h=200","price":"179元\n                            199元"},{"href":"https://www.mi.com/seckill","name":"米家飞利浦读写台灯 白色","desc":"双重防眩光，专为读写而生","imgurl":"//cdn.cnbj0.fds.api.mi-img.com/b2c-shopapi-pms/pms_1565058524.25058398.jpg?thumb=1&w=200&h=200","price":"499元\n                            569元"},{"href":"https://www.mi.com/seckill","name":"悦米YM人体工学椅 黑色","desc":"健康坐姿，舒适体验","imgurl":"//cdn.cnbj0.fds.api.mi-img.com/b2c-shopapi-pms/pms_1583380246.67713502.jpg?thumb=1&w=200&h=200","price":"1289元\n                            1399元"},{"href":"https://www.mi.com/seckill","name":"小米米家智能门锁 青春版 右开门","desc":"隐形指纹识别设计 简单一步快进家门","imgurl":"//cdn.cnbj0.fds.api.mi-img.com/b2c-shopapi-pms/pms_1563953645.84164836.jpg?thumb=1&w=200&h=200","price":"995元\n                            999元"},{"href":"https://www.mi.com/seckill","name":"小米小爱音箱HD 浅灰色","desc":"震撼嘹亮 音智同享","imgurl":"//cdn.cnbj1.fds.api.mi-img.com/mi-mall/93ef574280f48c407b6e7643c2b2636e.jpg?thumb=1&w=200&h=200&f=webp&q=90","price":"549元\n                            599元"},{"href":"https://www.mi.com/seckill","name":"小米米家视频门铃 单品","desc":"是门铃也是门前的护卫","imgurl":"//cdn.cnbj0.fds.api.mi-img.com/b2c-shopapi-pms/pms_1567752264.62688686.jpg?thumb=1&w=200&h=200","price":"239元\n                            269元"},{"href":"https://www.mi.com/seckill","name":"小米路由器4C 白色","desc":"300M单频，高增益4天线","imgurl":"//cdn.cnbj0.fds.api.mi-img.com/b2c-shopapi-pms/pms_1532604005.80875371.jpg?thumb=1&w=200&h=200","price":"59元\n                            99元"},{"href":"https://www.mi.com/seckill","name":"MIJOY 抽纸青春版 24包/箱 ","desc":"精选原生竹浆，健康环保","imgurl":"//cdn.cnbj0.fds.api.mi-img.com/b2c-shopapi-pms/pms_1571038766.41824452.jpg?thumb=1&w=200&h=200","price":"27.9元\n                            32.9元"},{"href":"https://www.mi.com/seckill","name":"米家电磁炉A1 黑色","desc":"9挡火力调节，2小时智能保温","imgurl":"//cdn.cnbj0.fds.api.mi-img.com/b2c-shopapi-pms/pms_1571725011.51156250.jpg?thumb=1&w=200&h=200","price":"128元\n                            149元"},{"href":"https://www.mi.com/seckill","name":"TOKIT迷你智能电烤箱 黑色","desc":"精致烤箱融合智能操控","imgurl":"//cdn.cnbj0.fds.api.mi-img.com/b2c-shopapi-pms/pms_1570690485.15255985.jpg?thumb=1&w=200&h=200","price":"499元\n                            599元"},{"href":"https://www.mi.com/seckill","name":"米兔积木 工程吊车 白色","desc":"手中的奇迹","imgurl":"//cdn.cnbj0.fds.api.mi-img.com/b2c-shopapi-pms/pms_1542247089.32395107.jpg?thumb=1&w=200&h=200","price":"148元\n                            169元"}][{"href":"https://www.mi.com/seckill","name":"小米圈铁四单元耳机 黑色","desc":"给热爱音乐的你","imgurl":"//cdn.cnbj0.fds.api.mi-img.com/b2c-shopapi-pms/pms_1571384720.99968563.jpg?thumb=1&w=200&h=200","price":"798元\n                            999元"},{"href":"https://www.mi.com/seckill","name":"玺佳机械表·T系列 太空TR90 红色","desc":"颠覆创新—腕间悬浮时光","imgurl":"//cdn.cnbj0.fds.api.mi-img.com/b2c-shopapi-pms/pms_1573198119.54049236.jpg?thumb=1&w=200&h=200","price":"499元\n                            599元"},{"href":"https://www.mi.com/seckill","name":"工程挖掘机 白色","desc":"全新炫酷外观，工程系列豪华升级","imgurl":"//cdn.cnbj0.fds.api.mi-img.com/b2c-shopapi-pms/pms_1572939589.21071305.jpg?thumb=1&w=200&h=200","price":"168元\n                            199元"},{"href":"https://www.mi.com/seckill","name":"小米净水器S1 800G 白色","desc":"RO反渗透精滤，直饮健康纯水","imgurl":"//cdn.cnbj0.fds.api.mi-img.com/b2c-shopapi-pms/pms_1573027813.58597871.jpg?thumb=1&w=200&h=200","price":"2499元\n                            2999元"},{"href":"https://www.mi.com/seckill","name":"米兔儿童滑板车 粉","desc":"安全好玩的酷玩具","imgurl":"//cdn.cnbj0.fds.api.mi-img.com/b2c-shopapi-pms/pms_1553483956.58434790.jpg?thumb=1&w=200&h=200","price":"219元\n                            249元"},{"href":"https://www.mi.com/seckill","name":"米家扫拖机器人 黑色","desc":"扫得干净，拖得彻底","imgurl":"//cdn.cnbj0.fds.api.mi-img.com/b2c-shopapi-pms/pms_1573714515.51751293.jpg?thumb=1&w=200&h=200","price":"1799元\n                            1999元"},{"href":"https://www.mi.com/seckill","name":"米家蓝牙温湿度计2 三个装","desc":"冷暖干湿,一望而知","imgurl":"//cdn.cnbj0.fds.api.mi-img.com/b2c-shopapi-pms/pms_1575878173.84429959.jpg?thumb=1&w=200&h=200","price":"69元\n                            87元"},{"href":"https://www.mi.com/seckill","name":"最生活毛巾·Air（10条装） 白色+素蓝","desc":"给生活一条好毛巾","imgurl":"//cdn.cnbj1.fds.api.mi-img.com/mi-mall/2212bbd7c00dbb8ed1db3d6b9ee2341c.jpg?thumb=1&w=200&h=200&f=webp&q=90","price":"99元\n                            169元"},{"href":"https://www.mi.com/seckill","name":"智能积木 越野四驱车 白色","desc":"搭建快乐，操控激情","imgurl":"//cdn.cnbj0.fds.api.mi-img.com/b2c-shopapi-pms/pms_1560161198.36395117.jpg?thumb=1&w=200&h=200","price":"689元\n                            699元"},{"href":"https://www.mi.com/seckill","name":"米家扫地机器人1S 白色","desc":"看得明白扫得彻底","imgurl":"//cdn.cnbj0.fds.api.mi-img.com/b2c-shopapi-pms/pms_1553760277.63282202.jpg?thumb=1&w=200&h=200","price":"1695元\n                            1999元"},{"href":"https://www.mi.com/seckill","name":"小米米家智能摄像机云台版 白","desc":"高清画质，守护家的每一面","imgurl":"//cdn.cnbj0.fds.api.mi-img.com/b2c-shopapi-pms/pms_1567393585.49577260.jpg?thumb=1&w=200&h=200","price":"179元\n                            199元"},{"href":"https://www.mi.com/seckill","name":"米家飞利浦读写台灯 白色","desc":"双重防眩光，专为读写而生","imgurl":"//cdn.cnbj0.fds.api.mi-img.com/b2c-shopapi-pms/pms_1565058524.25058398.jpg?thumb=1&w=200&h=200","price":"499元\n                            569元"},{"href":"https://www.mi.com/seckill","name":"悦米YM人体工学椅 黑色","desc":"健康坐姿，舒适体验","imgurl":"//cdn.cnbj0.fds.api.mi-img.com/b2c-shopapi-pms/pms_1583380246.67713502.jpg?thumb=1&w=200&h=200","price":"1289元\n                            1399元"},{"href":"https://www.mi.com/seckill","name":"小米米家智能门锁 青春版 右开门","desc":"隐形指纹识别设计 简单一步快进家门","imgurl":"//cdn.cnbj0.fds.api.mi-img.com/b2c-shopapi-pms/pms_1563953645.84164836.jpg?thumb=1&w=200&h=200","price":"995元\n                            999元"},{"href":"https://www.mi.com/seckill","name":"小米小爱音箱HD 浅灰色","desc":"震撼嘹亮 音智同享","imgurl":"//cdn.cnbj1.fds.api.mi-img.com/mi-mall/93ef574280f48c407b6e7643c2b2636e.jpg?thumb=1&w=200&h=200&f=webp&q=90","price":"549元\n                            599元"},{"href":"https://www.mi.com/seckill","name":"小米米家视频门铃 单品","desc":"是门铃也是门前的护卫","imgurl":"//cdn.cnbj0.fds.api.mi-img.com/b2c-shopapi-pms/pms_1567752264.62688686.jpg?thumb=1&w=200&h=200","price":"239元\n                            269元"},{"href":"https://www.mi.com/seckill","name":"小米路由器4C 白色","desc":"300M单频，高增益4天线","imgurl":"//cdn.cnbj0.fds.api.mi-img.com/b2c-shopapi-pms/pms_1532604005.80875371.jpg?thumb=1&w=200&h=200","price":"59元\n                            99元"},{"href":"https://www.mi.com/seckill","name":"MIJOY 抽纸青春版 24包/箱 ","desc":"精选原生竹浆，健康环保","imgurl":"//cdn.cnbj0.fds.api.mi-img.com/b2c-shopapi-pms/pms_1571038766.41824452.jpg?thumb=1&w=200&h=200","price":"27.9元\n                            32.9元"},{"href":"https://www.mi.com/seckill","name":"米家电磁炉A1 黑色","desc":"9挡火力调节，2小时智能保温","imgurl":"//cdn.cnbj0.fds.api.mi-img.com/b2c-shopapi-pms/pms_1571725011.51156250.jpg?thumb=1&w=200&h=200","price":"128元\n                            149元"},{"href":"https://www.mi.com/seckill","name":"TOKIT迷你智能电烤箱 黑色","desc":"精致烤箱融合智能操控","imgurl":"//cdn.cnbj0.fds.api.mi-img.com/b2c-shopapi-pms/pms_1570690485.15255985.jpg?thumb=1&w=200&h=200","price":"499元\n                            599元"},{"href":"https://www.mi.com/seckill","name":"米兔积木 工程吊车 白色","desc":"手中的奇迹","imgurl":"//cdn.cnbj0.fds.api.mi-img.com/b2c-shopapi-pms/pms_1542247089.32395107.jpg?thumb=1&w=200&h=200","price":"148元\n                            169元"}]